{
  "Abeille": "Abeille",
  "Ruche": "Ruche",
  "XiaomiBouton": "Xiaomi Bouton",
  "XiaomiBouton1": "Xiaomi Bouton 1",
  "XiaomiButtonSW86": "Xiaomi Bouton Carre 1 switch",
  "XiaomiPorte": "Xiaomi Porte",
  "XiaomiInfraRouge": "Xiaomi Infra Rouge",
  "XiaomiPrise": "Xiaomi Prise",
  "XiaomiTemperatureCarre": "Xiaomi Temperature Carré",
  "XiaomiTemperatureRond": "Xiaomi Temperature Rond",
  "IkeaTradfriBulbE27Opal1000lm": "IKEA TRADFRI bulb E27 opal 1000lm",
  "IkeaTradfri5BtnRond": "IKEA TRADFRI Rond 5 Boutons Remote Control",
  "HueGo": "Philips Hue Go",
  "HueWhite": "Philips Hue White",
  "Plug 01": "OSRAM Prise",
  "433": "RF433",
  "barometre": "Baromètre",
  "boiteauxlettres": "Boite aux Lettres",
  "chauffage": "Chauffage",
  "compteur": "Compteur",
  "contact": "Contact",
  "feuille": "Culture",
  "custom": "Custom",
  "dimmer": "Dimmer",
  "energie": "Energie",
  "garage": "Garage",
  "humidity": "Humidité",
  "humiditytemp": "Humidité et Température",
  "hydro": "Hydrométrie",
  "ir2": "Infra Rouge",
  "jauge": "Jauge",
  "light": "Luminosité",
  "meteo": "Météo",
  "motion": "Mouvement",
  "multisensor": "Multisensor",
  "prise": "Prise",
  "relay": "Relais",
  "rfid": "RFID",
  "teleinfo": "Téléinfo",
  "temp": "Température",
  "thermostat": "Thermostat",
  "volet": "Volet"
}