{
    "setReportRadiateurLocalTemperature": {
        "isVisible": 0,
        "name": "setReportRadiateurLocalTemperature",
        "isHistorized": "0",
        "subType": "other",
        "invertBinary": "0",
        "template": "",
        "configuration": {
            "topic": "setReport",
            "request": "targetEndpoint=01&ClusterId=0201&AttributeId=0000&AttributeType=29&MaxInterval=3500",
            "execAtCreation": "Yes",
            "execAtCreationDelay": "12",
            "visibilityCategory": "Network"
        },
        "type": "action"
    }
}